{
  "genesis_time": "2020-05-22T18:05:12.273013767Z",
  "chain_id": "dash-devnet-evonet-2",
  "consensus_params": {
    "block": {
      "max_bytes": "22020096",
      "max_gas": "-1",
      "time_iota_ms": "5000"
    },
    "evidence": {
      "max_age": "100000"
    },
    "validator": {
      "pub_key_types": [
        "ed25519"
      ]
    }
  },
  "validators": [
    {
      "address": "DE831C53E344F4D092BD9891952A31C4003003C0",
      "pub_key": {
        "type": "tendermint/PubKeyEd25519",
        "value": "1dQn/wIO4xYLAPths8KSVernZ5SnC0jR+A+7lUF7BGg="
      },
      "power": "1",
      "name": "masternode-1"
    }
  ,            {
      "address": "367685379CF74F92330649C23221ECCC9678FAF2",
      "pub_key": {
        "type": "tendermint/PubKeyEd25519",
        "value": "uP2tDRwQwlFgS7pqkVe1DfVa/ciAdEVbW3KhKq7/mN8="
      },
      "power": "1",
      "name": "masternode-2"
    }
  ,            {
      "address": "A7567FCBE0B2EDC9A6E349284164AE4AD95DC7E1",
      "pub_key": {
        "type": "tendermint/PubKeyEd25519",
        "value": "b1eKkkMTd4QQt9WeAqNA0v9IsORYCscQgE9TMObPCV0="
      },
      "power": "1",
      "name": "masternode-3"
    }
  ,            {
      "address": "B69E73788137AF30AF83F48329BC6B7E7F61254A",
      "pub_key": {
        "type": "tendermint/PubKeyEd25519",
        "value": "i43mZ49NV/PKifhfIbo+WczLWP6mRxPG9MyMWNB+sGE="
      },
      "power": "1",
      "name": "masternode-4"
    }
  ,            {
      "address": "6F5F90D5F5A3D26DA4F2DD783F80C970F5EB8922",
      "pub_key": {
        "type": "tendermint/PubKeyEd25519",
        "value": "+FjEx+CcVwo9eb4nnZ424FR+jVG83O8ZgEUF5x+tHVs="
      },
      "power": "1",
      "name": "masternode-5"
    }
  ,            {
      "address": "DC73204881AD5AEB9C8DB8769ADD2BEF10660328",
      "pub_key": {
        "type": "tendermint/PubKeyEd25519",
        "value": "CDX0R2Fyf1Or/+5vngvYBk+T4BS29YldpQJ8R1Wiync="
      },
      "power": "1",
      "name": "masternode-6"
    }
  ,            {
      "address": "81582DD4BF59600678323EA3F8AF6884F1FF5380",
      "pub_key": {
        "type": "tendermint/PubKeyEd25519",
        "value": "6S/Fr3TCKWtddmiyHI5tRk/R4qHywh2mfATw6pLrGZ4="
      },
      "power": "1",
      "name": "masternode-7"
    }
  ,            {
      "address": "99B5C4E9DFEF4ECC06DC4ACD34D5608CCC9247B8",
      "pub_key": {
        "type": "tendermint/PubKeyEd25519",
        "value": "tdSB3lbc85cVyREcrNxnUNkjcBg2LAobsBNtuqOWDVU="
      },
      "power": "1",
      "name": "masternode-8"
    }
  ,            {
      "address": "DA66978D88DDCB5C89491A8ED142B7F3A894BD72",
      "pub_key": {
        "type": "tendermint/PubKeyEd25519",
        "value": "395JWUe60WdTbtmz/RLgo/lXMkgn2WLxyzdmQ2lZl1s="
      },
      "power": "1",
      "name": "masternode-9"
    }
  ,            {
      "address": "4D3C881026E4CFD801768FF6739DC958D1766056",
      "pub_key": {
        "type": "tendermint/PubKeyEd25519",
        "value": "GWlZ+zzDwn4I5CsbvjgeWju4pXqXqWZqNgvDBQ1g5Ec="
      },
      "power": "1",
      "name": "masternode-10"
    }
  ,            {
      "address": "76A80A8025AE8EB9A086C3376F971BC0391B4C12",
      "pub_key": {
        "type": "tendermint/PubKeyEd25519",
        "value": "+7iEi/FWs8AiQEyCLAgl5iNsOY1hT2pknLT0YWeLXd8="
      },
      "power": "1",
      "name": "masternode-11"
    }
  ,            {
      "address": "48B375876BCCDB5FCDA1402FE48AF4BCAB3240A4",
      "pub_key": {
        "type": "tendermint/PubKeyEd25519",
        "value": "qiYB+xjSVFZvMUM6sl1UUX9QULwgf462Ge+8uxV6Y+M="
      },
      "power": "1",
      "name": "masternode-12"
    }
  ,            {
      "address": "31A1AA26A83B9901B2A738B43CA5645ECD1F6675",
      "pub_key": {
        "type": "tendermint/PubKeyEd25519",
        "value": "IIxHwIxMoxq7+wwtLAmQ2Phz8rEYn1i3kFaZau2Q0VY="
      },
      "power": "1",
      "name": "masternode-13"
    }
  ,            {
      "address": "49B3F8E8BAEFBD3FB6BBED4128499FBA198229DD",
      "pub_key": {
        "type": "tendermint/PubKeyEd25519",
        "value": "Z7SGPBWhnDQMXWK6nRIPTLDv7/e0/WJ0GMPXqvebL9c="
      },
      "power": "1",
      "name": "masternode-14"
    }
  ,            {
      "address": "853A303CDCEC91E22D6856DF2B5C7127153AD56A",
      "pub_key": {
        "type": "tendermint/PubKeyEd25519",
        "value": "f9M6FQjel+HpbmQThXsneowwEGEozDv0FnyYWJF7qFE="
      },
      "power": "1",
      "name": "masternode-15"
    }
  ,            {
      "address": "9480860DB56F367539FC889CA48A542E8FD1C6F7",
      "pub_key": {
        "type": "tendermint/PubKeyEd25519",
        "value": "8le4VSJ+nnK4D6xz8kAJ15NIljgq3ray6DoQ050UJYE="
      },
      "power": "1",
      "name": "masternode-16"
    }
  ,            {
      "address": "1364708F9EA9A8CCC4E2CC8EE14996A276501A02",
      "pub_key": {
        "type": "tendermint/PubKeyEd25519",
        "value": "R5a9kXGFyStCLHLL3Uqq27pam8Gze4WJp1H2mX9Bc0I="
      },
      "power": "1",
      "name": "masternode-17"
    }
  ,            {
      "address": "63A620E1F8AFE629A0B23E4125D211037B33213C",
      "pub_key": {
        "type": "tendermint/PubKeyEd25519",
        "value": "NT3DeGs6Da3Y1laKytR1XTOsosRAd2eV+DuLfTAVvnM="
      },
      "power": "1",
      "name": "masternode-18"
    }
  ,            {
      "address": "93CEDB93F092517D083A0AD9352778912D3408D4",
      "pub_key": {
        "type": "tendermint/PubKeyEd25519",
        "value": "KmDxYd/kfnZ/c3II5OaK91nXahzxC9uF+PjI1dqJqXU="
      },
      "power": "1",
      "name": "masternode-19"
    }
  ,            {
      "address": "BC404827CEA12BDDAD81ECD4708B0E98FA6164F6",
      "pub_key": {
        "type": "tendermint/PubKeyEd25519",
        "value": "jBZbYuCt4kZIs/IvDqcydg7Q1tQMsvWCImscZgq5uNo="
      },
      "power": "1",
      "name": "masternode-20"
    }
  ,            {
      "address": "12FA1892F47D28B7FFB3E6A59023A7D0D5FF3DBE",
      "pub_key": {
        "type": "tendermint/PubKeyEd25519",
        "value": "T2LTYs95HTmiHgffh+xMEF1HO/bIRCs2X/C/KBvnMHs="
      },
      "power": "1",
      "name": "masternode-21"
    }
  ,            {
      "address": "737FFDA04638EC5866C235471652775503AC3B19",
      "pub_key": {
        "type": "tendermint/PubKeyEd25519",
        "value": "fKRFw/D9gbLYXAtS00Qr/UpJzy571aLF/dFCKAyNqvY="
      },
      "power": "1",
      "name": "masternode-22"
    }
  ,            {
      "address": "2D37B8A27E92590EE7F2ABD23F8902C29B76AEF4",
      "pub_key": {
        "type": "tendermint/PubKeyEd25519",
        "value": "VqdWrrDgkL3YokuuLKDZwmW4U4a3vlpWpRDznQ24AKk="
      },
      "power": "1",
      "name": "masternode-23"
    }
  ,            {
      "address": "356BEEEDFAB0282B629EF0331CD479913EC86B82",
      "pub_key": {
        "type": "tendermint/PubKeyEd25519",
        "value": "hLtKDz03HjrkmBJwcDWyh3+pCnOTE/DiOVguEbQQ9JA="
      },
      "power": "1",
      "name": "masternode-24"
    }
  ,            {
      "address": "D08398EABFFB5788E9697022E580C3BB30579EDF",
      "pub_key": {
        "type": "tendermint/PubKeyEd25519",
        "value": "E9mjcf2TP1iziaxdRG5/7UuewLRWIQNpmvQgt1NSz7s="
      },
      "power": "1",
      "name": "masternode-25"
    }
  ,            {
      "address": "45C32C068C5359007FE9F7B33D1F0FDDCCF0AEF5",
      "pub_key": {
        "type": "tendermint/PubKeyEd25519",
        "value": "SYhxf9fC6UY4+BYPdkUCsTIh52BzigO1AoAloTWXjJI="
      },
      "power": "1",
      "name": "masternode-26"
    }
  ,            {
      "address": "09F30C12D1C12EF3CE0FB5E603DD654B9E145CA7",
      "pub_key": {
        "type": "tendermint/PubKeyEd25519",
        "value": "kq5gomJFRWg2Xz9zX1Qr8pN/ypTkp5VhjG5HeTPWXRA="
      },
      "power": "1",
      "name": "masternode-27"
    }
  ,            {
      "address": "2B609F61A50318F58DD2BC46C7E5C0BDD98D40F5",
      "pub_key": {
        "type": "tendermint/PubKeyEd25519",
        "value": "3+sNYZAKWepp3sLY+k9qLNUmONO5OCsUPfLD301Cov8="
      },
      "power": "1",
      "name": "masternode-28"
    }
  ,            {
      "address": "05F9591FB3AC8609AC466251944108FA03E055FB",
      "pub_key": {
        "type": "tendermint/PubKeyEd25519",
        "value": "+zZ4l7jZngXBamCDvpJG/c9BJCpyq4BlqO2uhFM+UW8="
      },
      "power": "1",
      "name": "masternode-29"
    }
  ,            {
      "address": "3401130CC62B47C1D6EE15F6C76B385E26CDC87E",
      "pub_key": {
        "type": "tendermint/PubKeyEd25519",
        "value": "10jYmIz/xzJqS02boki4olBllG771zYt8OralqEghp0="
      },
      "power": "1",
      "name": "masternode-30"
    }
  ,            {
      "address": "7CC1ABCD21C543D8D55A5AA15B0C760BCA91AC39",
      "pub_key": {
        "type": "tendermint/PubKeyEd25519",
        "value": "UWo93goay5Qw5jxrBGOYX/EJi03Xjt0h9O9c6pmWY7s="
      },
      "power": "1",
      "name": "masternode-31"
    }
  ,            {
      "address": "A4AB933B78DE996D4266D62ED886CBE7B536F56B",
      "pub_key": {
        "type": "tendermint/PubKeyEd25519",
        "value": "67PUS4EAcAk5tXtBY4jCr5No1A7eKy+SbARhdTcRuJg="
      },
      "power": "1",
      "name": "masternode-32"
    }
  ,            {
      "address": "C07E0F6C07C20A8265476362CE2821EAD8AD16E7",
      "pub_key": {
        "type": "tendermint/PubKeyEd25519",
        "value": "PMVCOAp1iQ7pwClBGa/Y1N3ZC/0MjMtvpbVhf2PtPQs="
      },
      "power": "1",
      "name": "masternode-33"
    }
  ,            {
      "address": "25D2754CB94121C83A7BAAFE4F43651BB354011F",
      "pub_key": {
        "type": "tendermint/PubKeyEd25519",
        "value": "3aJWZuVO1/CTfBE4CHNVxI7EKB6UwzIT2i47Ra1wG1s="
      },
      "power": "1",
      "name": "masternode-34"
    }
  ,            {
      "address": "BD4D294FF572976F41FE2979F8257278E0CDBCA3",
      "pub_key": {
        "type": "tendermint/PubKeyEd25519",
        "value": "bUhYLGsyXMiPf27YNlNBP1GTwiYjM3kk3dcV/pgTM/8="
      },
      "power": "1",
      "name": "masternode-35"
    }
  ,            {
      "address": "92F07BB198244CE703EC0A29F5FC3475395F0B7A",
      "pub_key": {
        "type": "tendermint/PubKeyEd25519",
        "value": "d5zfgEyZU95CyZOz0EuZ53MoK3NvEbNIc/dx8SQvINE="
      },
      "power": "1",
      "name": "masternode-36"
    }
  ,            {
      "address": "7F58DAB35D39ED5D7E38F5F7A36EE5D5FF19662C",
      "pub_key": {
        "type": "tendermint/PubKeyEd25519",
        "value": "AZcKyLkzr4y0ZGgr5ijDOBQxdlkNUQk9LspNDB1KXDI="
      },
      "power": "1",
      "name": "masternode-37"
    }
  ,            {
      "address": "A8861ED2CDA219C80D23BABFB5BEA0E2AA61F584",
      "pub_key": {
        "type": "tendermint/PubKeyEd25519",
        "value": "egZjk2i6gBNfBo/yPTvsTgCvbFXsKOxFJ2YMkfwjymQ="
      },
      "power": "1",
      "name": "masternode-38"
    }
  ,            {
      "address": "23DA033CD3F50302DDB4F9E9B1963D625BB3E95C",
      "pub_key": {
        "type": "tendermint/PubKeyEd25519",
        "value": "jR4wURePxo2jO0eJ4LHq1j0x5dQapT0LgNd4tHPTWwE="
      },
      "power": "1",
      "name": "masternode-39"
    }
  ,            {
      "address": "658FEE55CC25A521420C63ECEF23F0240A7E42F0",
      "pub_key": {
        "type": "tendermint/PubKeyEd25519",
        "value": "Mx4OgZkzefO4eJRo+3wnazaTSRNiispaRDqTUPz5fPU="
      },
      "power": "1",
      "name": "masternode-40"
    }
  ,            {
      "address": "CC6287DFFC34B4D906848654386D7B3EBAB6956E",
      "pub_key": {
        "type": "tendermint/PubKeyEd25519",
        "value": "unc92BAwK5jBwlyIRg5Wbp9WxEV9fBn/gQjCZ2wB99U="
      },
      "power": "1",
      "name": "masternode-41"
    }
  ,            {
      "address": "A997478E30061F0A7D89F2416E5E8CBAD9736256",
      "pub_key": {
        "type": "tendermint/PubKeyEd25519",
        "value": "o9SgNvDmTK9A6Crf2WpN+nICbgYjo2iH5u0AslBupaI="
      },
      "power": "1",
      "name": "masternode-42"
    }
  ,            {
      "address": "4B68F8BE3B1D8BD9DCE33D176087B14086D89B0A",
      "pub_key": {
        "type": "tendermint/PubKeyEd25519",
        "value": "cfy0fjdzPSINKzAGNHjFZNVhMvU1RDSTV1WVRHciQpE="
      },
      "power": "1",
      "name": "masternode-43"
    }
  ,            {
      "address": "C8924EC8CAFABEFD158F923978915E906646CFAB",
      "pub_key": {
        "type": "tendermint/PubKeyEd25519",
        "value": "pOILwLwmSexbnfzqibZch/m9vKFn/zKUhr9e1r/FNck="
      },
      "power": "1",
      "name": "masternode-44"
    }
  ,            {
      "address": "542F1E0ACC6F7B63D26DECD59F57D167FE2C3B82",
      "pub_key": {
        "type": "tendermint/PubKeyEd25519",
        "value": "DMfQxnJT3PHayKfplqfyLM5OvdCUCrHpbege2aaW2sU="
      },
      "power": "1",
      "name": "masternode-45"
    }
  ,            {
      "address": "457007DF4DD09ADDC3DA93FD777C5370141EB9F4",
      "pub_key": {
        "type": "tendermint/PubKeyEd25519",
        "value": "FSgUvKIL2rV1tnwBK4eKFcV8zqqStB23x20KKFjc/+k="
      },
      "power": "1",
      "name": "masternode-46"
    }
  ,            {
      "address": "F992C58BC04C11E26F2A5D6401B8AF2DBA75D4B0",
      "pub_key": {
        "type": "tendermint/PubKeyEd25519",
        "value": "nPbOiVyGZEasyFwnawm65Pmqzi0zoyMcdD6lkzvFEg0="
      },
      "power": "1",
      "name": "masternode-47"
    }
  ,            {
      "address": "6A2ACC10E20213D4EA285303D4D81DCE2B5E323C",
      "pub_key": {
        "type": "tendermint/PubKeyEd25519",
        "value": "tcDk3CmGvFPfMja4mHGfRUt8KHd06ND4DrvvfCcDYjE="
      },
      "power": "1",
      "name": "masternode-48"
    }
  ,            {
      "address": "8D898D753306BF83A47B424F6014DF7E46393545",
      "pub_key": {
        "type": "tendermint/PubKeyEd25519",
        "value": "iIPq6t2mTAElCTzBWHfvOrJq2anvo2Zb1sLX9V/Tx9Y="
      },
      "power": "1",
      "name": "masternode-49"
    }
  ,            {
      "address": "AD1AFF0377BB7B1239402BB4B88D712FD1FE90A0",
      "pub_key": {
        "type": "tendermint/PubKeyEd25519",
        "value": "la0th0Iu7DhdC09uckB+IJNvQ0g9uUfrccf5PikngHE="
      },
      "power": "1",
      "name": "masternode-50"
    }
  ],
  "app_hash": ""
}
